{
  "id": "representation",
  "type": "SharedSlice",
  "name": "Representation",
  "description": "Representation",
  "variations": [
    {
      "id": "default",
      "name": "Default",
      "docURL": "...",
      "version": "initial",
      "description": "Default",
      "imageUrl": "",
      "primary": {
        "representation": {
          "type": "Group",
          "config": {
            "label": "representation",
            "repeat": true,
            "fields": {
              "image": {
                "type": "Image",
                "config": {
                  "label": "image",
                  "constraint": {},
                  "thumbnails": []
                }
              },
              "title": {
                "type": "Text",
                "config": {
                  "label": "title",
                  "placeholder": ""
                }
              },
              "description": {
                "type": "StructuredText",
                "config": {
                  "label": "description",
                  "placeholder": "",
                  "allowTargetBlank": true,
                  "multi": "paragraph,preformatted,heading1,heading2,heading3,heading4,heading5,heading6,strong,em,hyperlink,image,embed,list-item,o-list-item,rtl"
                }
              },
              "talent_name": {
                "type": "Text",
                "config": {
                  "label": "talent name",
                  "placeholder": ""
                }
              },
              "talent_link": {
                "type": "Link",
                "config": {
                  "label": "talent link",
                  "select": "document"
                }
              }
            }
          }
        }
      },
      "items": {}
    }
  ]
}
